yellowduck/__init__.py
yellowduck/etc/__init__.py
yellowduck/etc/id_card_validator.py
yellowduck/image/__init__.py
yellowduck/image/grouping.py
yellowduck/image/image.py
yellowduck/image/utils.py
yellowduck/text/__init__.py
yellowduck/text/cleansing.py
yellowduck/text/grouping.py
yellowduck-1.1.0.dist-info/LICENSE
yellowduck-1.1.0.dist-info/METADATA
yellowduck-1.1.0.dist-info/WHEEL
yellowduck-1.1.0.dist-info/top_level.txt
yellowduck-1.1.0.dist-info/RECORD
