Metadata-Version: 2.1
Name: yellowduck
Version: 1.1.0
Summary: Data Science Toolbox for everyone
Home-page: https://github.com/PCP55/yellowduck
Author: Chalat Phumphiraratthaya
Author-email: chalat.phum@gmail.com
Classifier: Programming Language :: Python :: 3.6
Classifier: License :: OSI Approved :: MIT License
Classifier: Topic :: Scientific/Engineering
Requires-Python: >=3.6
License-File: LICENSE
Requires-Dist: black >=22.12.0
Requires-Dist: flake8 >=6.0.0
Requires-Dist: pep8-naming >=0.13.3
Requires-Dist: isort >=5.11.5
Requires-Dist: pre-commit >=2.21.0
Requires-Dist: scikit-learn >=1.0.0
Provides-Extra: full
Requires-Dist: fuzzywuzzy >=0.18.0 ; extra == 'full'
Requires-Dist: pythainlp >=2.3.2 ; extra == 'full'
Requires-Dist: strsimpy >=0.2.1 ; extra == 'full'
Requires-Dist: cryptography >=36.0.2 ; extra == 'full'
Requires-Dist: pycryptodome >=3.9.7 ; extra == 'full'
Provides-Extra: image
Requires-Dist: cryptography >=36.0.2 ; extra == 'image'
Requires-Dist: pycryptodome >=3.9.7 ; extra == 'image'
Provides-Extra: text
Requires-Dist: fuzzywuzzy >=0.18.0 ; extra == 'text'
Requires-Dist: pythainlp >=2.3.2 ; extra == 'text'
Requires-Dist: strsimpy >=0.2.1 ; extra == 'text'
